icoco/VERSION
icoco/__init__.py
icoco/exception.py
icoco/problem.py
icoco/utils.py
icoco/version.py
icoco-2.0.6.dist-info/licenses/LICENSE
icoco-2.0.6.dist-info/METADATA
icoco-2.0.6.dist-info/WHEEL
icoco-2.0.6.dist-info/top_level.txt
icoco-2.0.6.dist-info/RECORD
